pytube/__init__.py
pytube/__main__.py
pytube/captions.py
pytube/cipher.py
pytube/cli.py
pytube/exceptions.py
pytube/extract.py
pytube/helpers.py
pytube/innertube.py
pytube/itags.py
pytube/metadata.py
pytube/monostate.py
pytube/parser.py
pytube/query.py
pytube/request.py
pytube/streams.py
pytube/version.py
pytube/contrib/__init__.py
pytube/contrib/channel.py
pytube/contrib/playlist.py
pytube/contrib/search.py
pytube_local_0813-0.6.0.dist-info/LICENSE
pytube_local_0813-0.6.0.dist-info/METADATA
pytube_local_0813-0.6.0.dist-info/WHEEL
pytube_local_0813-0.6.0.dist-info/entry_points.txt
pytube_local_0813-0.6.0.dist-info/top_level.txt
pytube_local_0813-0.6.0.dist-info/zip-safe
pytube_local_0813-0.6.0.dist-info/RECORD
